gps_activity/__init__.py
gps_activity/abstract.py
gps_activity/extraction/__init__.py
gps_activity/extraction/facade.py
gps_activity/extraction/factory/__init__.py
gps_activity/extraction/factory/classifiers/__init__.py
gps_activity/extraction/factory/clustering/__init__.py
gps_activity/extraction/factory/clustering/fdbscan.py
gps_activity/extraction/factory/clustering/stcm.py
gps_activity/extraction/factory/fragmentation/__init__.py
gps_activity/extraction/factory/fragmentation/velocity.py
gps_activity/extraction/factory/preprocessing.py
gps_activity/extraction/nodes/__init__.py
gps_activity/extraction/nodes/fdbscan.py
gps_activity/extraction/nodes/stcm.py
gps_activity/extraction/nodes/velocity_fragmentator.py
gps_activity/linker/__init__.py
gps_activity/linker/facade.py
gps_activity/linker/factory/__init__.py
gps_activity/linker/factory/cluster_aggregator.py
gps_activity/linker/factory/coverage_statistics.py
gps_activity/linker/factory/join_validator.py
gps_activity/linker/factory/preprocessing.py
gps_activity/linker/factory/spatial_joiner.py
gps_activity/linker/models.py
gps_activity/linker/nodes/__init__.py
gps_activity/linker/nodes/cluster_aggregator.py
gps_activity/linker/nodes/coverage_statistics.py
gps_activity/linker/nodes/spatial_join_validator.py
gps_activity/linker/nodes/spatial_joiner.py
gps_activity/metrics/__init__.py
gps_activity/metrics/facade.py
gps_activity/metrics/models.py
gps_activity/metrics/nodes/__init__.py
gps_activity/metrics/nodes/fbeta.py
gps_activity/metrics/nodes/precision.py
gps_activity/metrics/nodes/recall.py
gps_activity/models.py
gps_activity/nodes/__init__.py
gps_activity/nodes/coordinates_velocity_calculator.py
gps_activity/nodes/crs_projection.py
gps_activity/nodes/date_extractor.py
gps_activity/nodes/df_to_gdf.py
gps_activity/nodes/formatting.py
gps_activity/nodes/order_gps.py
gps_activity/nodes/primary_key_generator.py
gps_activity/nodes/project_default_fields.py
gps_activity/nodes/schema_validator.py
gps_activity-0.7.3.dist-info/LICENSE.txt
gps_activity-0.7.3.dist-info/METADATA
gps_activity-0.7.3.dist-info/WHEEL
gps_activity-0.7.3.dist-info/RECORD
