Metadata-Version: 2.1
Name: gps-activity
Version: 0.7.3
Summary: A light-weight mobile module for analysis of GPS activity
License: LICENSE.txt
Author: Adil Rashitov
Author-email: adil@wastelab.com
Requires-Python: >=3.8.1,<3.12
Classifier: Intended Audience :: Developers
Classifier: Intended Audience :: Science/Research
Classifier: License :: Other/Proprietary License
Classifier: Operating System :: OS Independent
Classifier: Programming Language :: Python
Classifier: Programming Language :: Python :: 3
Classifier: Programming Language :: Python :: 3.9
Classifier: Programming Language :: Python :: 3.10
Classifier: Programming Language :: Python :: 3.11
Classifier: Programming Language :: Python :: 3.8
Classifier: Topic :: Scientific/Engineering
Classifier: Topic :: Software Development
Requires-Dist: geopandas (==0.12.2)
Requires-Dist: numpy (>=1.24.3,<2.0.0)
Requires-Dist: pandas (>=2.0.1,<3.0.0)
Requires-Dist: pandera (>=0.15.1,<0.16.0)
Requires-Dist: scikit-learn (>=1.2.2,<2.0.0)
